{"title":"about","uid":"03933793d01427bd4ef056d0a9b02560","text":" 学习笔记 ！笔记！笔记！所有内容只是学习研究！！！ ","date":"2021-08-18T07:03:03.000Z","updated":"2023-04-21T12:00:00.025Z","comments":true,"path":"api/pages/about/index.json","covers":[],"excerpt":"","content":"<meta name=\"referrer\" content=\"no-referrer\"/>\n\n<h1 id=\"学习笔记-！笔记！笔记！\"><a href=\"#学习笔记-！笔记！笔记！\" class=\"headerlink\" title=\"学习笔记 ！笔记！笔记！\"></a>学习笔记 ！笔记！笔记！</h1><h1 id=\"所有内容只是学习研究！！！\"><a href=\"#所有内容只是学习研究！！！\" class=\"headerlink\" title=\"所有内容只是学习研究！！！\"></a>所有内容只是学习研究！！！</h1><p><img src=\"https://cdn.nlark.com/yuque/0/2023/jpeg/25696976/1682078383856-00422cf2-c600-45ed-aace-0f751246a805.jpeg?x-oss-process=image/interlace,1\" alt=\"img\"></p>\n","count_time":{"symbolsCount":28,"symbolsTime":"1 mins."},"toc":"<ol class=\"toc\"><li class=\"toc-item toc-level-1\"><a class=\"toc-link\" href=\"#%E5%AD%A6%E4%B9%A0%E7%AC%94%E8%AE%B0-%EF%BC%81%E7%AC%94%E8%AE%B0%EF%BC%81%E7%AC%94%E8%AE%B0%EF%BC%81\"><span class=\"toc-text\">学习笔记 ！笔记！笔记！</span></a></li><li class=\"toc-item toc-level-1\"><a class=\"toc-link\" href=\"#%E6%89%80%E6%9C%89%E5%86%85%E5%AE%B9%E5%8F%AA%E6%98%AF%E5%AD%A6%E4%B9%A0%E7%A0%94%E7%A9%B6%EF%BC%81%EF%BC%81%EF%BC%81\"><span class=\"toc-text\">所有内容只是学习研究！！！</span></a></li></ol>"}